dragoneye/__init__.py
dragoneye/config.py
dragoneye/config.yaml
dragoneye/dragoneye_exception.py
dragoneye/scan.py
dragoneye/version.py
dragoneye/cloud_scanner/__init__.py
dragoneye/cloud_scanner/base_cloud_scanner.py
dragoneye/cloud_scanner/aws/__init__.py
dragoneye/cloud_scanner/aws/aws_scan_settings.py
dragoneye/cloud_scanner/aws/aws_scanner.py
dragoneye/cloud_scanner/aws/aws_session_factory.py
dragoneye/cloud_scanner/azure/__init__.py
dragoneye/cloud_scanner/azure/azure_authorizer.py
dragoneye/cloud_scanner/azure/azure_scan_settings.py
dragoneye/cloud_scanner/azure/azure_scanner.py
dragoneye/cloud_scanner/gcp/__init__.py
dragoneye/cloud_scanner/gcp/gcp_credentials_factory.py
dragoneye/cloud_scanner/gcp/gcp_scan_settings.py
dragoneye/cloud_scanner/gcp/gcp_scanner.py
dragoneye/utils/__init__.py
dragoneye/utils/app_logger.py
dragoneye/utils/boto_backoff.py
dragoneye/utils/misc_utils.py
dragoneye/utils/threading_utils.py
dragoneye/utils/value_validator.py
dragoneye-0.0.77.dist-info/LICENSE
dragoneye-0.0.77.dist-info/METADATA
dragoneye-0.0.77.dist-info/WHEEL
dragoneye-0.0.77.dist-info/entry_points.txt
dragoneye-0.0.77.dist-info/top_level.txt
dragoneye-0.0.77.dist-info/RECORD
