Metadata-Version: 2.1
Name: dragoneye
Version: 0.0.77
Summary: Multi-cloud data scan tool
Home-page: https://github.com/indeni/dragoneye
Author: Indeni
Author-email: engineering@indeni.com
License: UNKNOWN
Keywords: cloud,aws,azure,scan
Platform: UNKNOWN
Classifier: Development Status :: 3 - Alpha
Classifier: Intended Audience :: Developers
Classifier: License :: OSI Approved :: MIT License
Classifier: Programming Language :: Python :: 3.7
Classifier: Programming Language :: Python :: 3.8
Classifier: Programming Language :: Python :: 3.9
License-File: LICENSE
Requires-Dist: pyjq (>=2.3.1)
Requires-Dist: boto3 (>=1.17.22)
Requires-Dist: PyYAML (>=5.3.1)
Requires-Dist: backoff (>=1.10.0)
Requires-Dist: requests (>=2.22.0)
Requires-Dist: click (>=7.1.2)
Requires-Dist: click-aliases (>=1.0.1)
Requires-Dist: oauth2client (>=4.1.3)
Requires-Dist: google-api-python-client (>=2.9.0)
